.DS_Store
multisesh/AlignExtract.py
multisesh/Classes.py
multisesh/FindCentres.py
multisesh/LabelVideo.py
multisesh/OutDir.py
multisesh/__init__.py
multisesh/errorMessages.py
multisesh/exceptions.py
multisesh/findMeta.py
multisesh/generalFunctions.py
multisesh/macros.py
multisesh/noMergeStitch.py
multisesh/thresh_utils.py
multisesh/untitled.py
multisesh/zProj.py
multisesh-0.0.24.dist-info/METADATA
multisesh-0.0.24.dist-info/WHEEL
multisesh-0.0.24.dist-info/top_level.txt
multisesh-0.0.24.dist-info/RECORD
