Metadata-Version: 2.1
Name: multisesh
Version: 0.0.24
Summary: For combining and analysing microscope imaging data made in multiple different sessions.
Home-page: https://github.com/TomPJWyatt/MultiSesh
Author: Tom Wyatt
Author-email: womtyatt@gmail.com
Classifier: Programming Language :: Python :: 3
Classifier: License :: OSI Approved :: MIT License
Classifier: Operating System :: OS Independent
Requires-Dist: tifffile
Requires-Dist: numpy (>=1.19.4)
Requires-Dist: scipy (>=1.5.3)
Requires-Dist: opencv-python (>=4.5.0)
Requires-Dist: scikit-image
Requires-Dist: scyjava
Requires-Dist: matplotlib
Requires-Dist: aicsimageio
